MANIFEST.in
README.rst
setup.py
man/git-geo.1
src/geocommit/__init__.py
src/geocommit/location.py
src/geocommit/locationprovider.py
src/geocommit/networkmanager.py
src/geocommit/tests.py
src/geocommit/util.py
src/geocommit/wifilocationprovider.py
src/geocommit.egg-info/PKG-INFO
src/geocommit.egg-info/SOURCES.txt
src/geocommit.egg-info/dependency_links.txt
src/geocommit.egg-info/entry_points.txt
src/geocommit.egg-info/requires.txt
src/geocommit.egg-info/top_level.txt
src/geocommit/provider/__init__.py
src/geocommit/provider/corelocation/__init__.py
src/geocommit/provider/corelocation/geocommit.m
src/geocommit/provider/corelocation/geocommitdelegate.h
src/geocommit/provider/corelocation/geocommitdelegate.m