Metadata-Version: 1.0
Name: geocommit
Version: 0.9.2
Summary: Geolocation for git
Home-page: http://pypi.python.org/geocommit
Author: Nils Adermann <naderman+geocommit@naderman.de>, Filip Noetzel <filip+geocommit@j03.de>, David Soria Parra <dsp+geocommit@experimentalworks.net>
Author-email: filip+geocommit@j03.de
License: Beerware
Keywords: git geo
Platform: UNKNOWN
